synapticsync/__init__.py
synapticsync/behavior/__init__.py
synapticsync/behavior/behavioral_epoch_tools.py
synapticsync/behavior/boris_extraction.py
synapticsync/behavior/ecu_extraction.py
synapticsync/lfp/LFP_collection.py
synapticsync/lfp/LFP_recording.py
synapticsync/lfp/README.md
synapticsync/lfp/__init__.py
synapticsync/lfp/connectivity_wrapper.py
synapticsync/lfp/decoders.py
synapticsync/lfp/event_extraction.py
synapticsync/lfp/plotting.py
synapticsync/lfp/preprocessor.py
synapticsync/spike/README.md
synapticsync/spike/__init__.py
synapticsync/spike/decoders.py
synapticsync/spike/firing_rate_calculations.py
synapticsync/spike/normalization.py
synapticsync/spike/pca_trajectories.py
synapticsync/spike/single_cell.py
synapticsync/spike/spike_collection.py
synapticsync/spike/spike_recording.py
synapticsync/utils.py
synapticsync-0.0.0a2.dist-info/LICENSE
synapticsync-0.0.0a2.dist-info/METADATA
synapticsync-0.0.0a2.dist-info/WHEEL
synapticsync-0.0.0a2.dist-info/RECORD
